{"sections":{"main":{"type":"blog-template","settings":{"blog_show_rss":false,"blog_show_tags":true,"blog_show_date":false,"blog_show_comments":false,"blog_show_author":false,"blog_image_size":"wide"}},"sidebar":{"type":"blog-sidebar","blocks":{"tags":{"type":"tags","settings":{}},"cd0e249b-164f-49cc-a381-cddf45fedaab":{"type":"share","settings":{}},"112ed65c-456a-416a-915c-01766e4ad0da":{"type":"article","settings":{"title":"Popular posts","article":"","blog_show_tags":true,"blog_show_date":true,"blog_show_comments":true,"blog_show_author":false,"blog_image_size":"wide"}}},"block_order":["tags","cd0e249b-164f-49cc-a381-cddf45fedaab","112ed65c-456a-416a-915c-01766e4ad0da"],"settings":{}},"featured-collections":{"type":"featured-collections","blocks":{"collection1":{"type":"collection","disabled":true,"settings":{"collection":"","title":""}},"collection2":{"type":"collection","settings":{"collection":"","title":""}},"collection3":{"type":"collection","settings":{"collection":"","title":""}},"collection4":{"type":"collection","settings":{"collection":"","title":""}},"collection5":{"type":"collection","settings":{"collection":"","title":""}},"collection6":{"type":"collection","settings":{"collection":"","title":""}}},"block_order":["collection1","collection2","collection3","collection4","collection5","collection6"],"settings":{"title":"You may also like","divider":false}}},"order":["main","sidebar","featured-collections"],"wrapper":"div.page-width.page-content.blog-layout"}